jupyter_dash/__init__.py
jupyter_dash/comms.py
jupyter_dash/jupyter_app.py
jupyter_dash/server_tools.py
jupyter_dash/version.py
jupyter_dash/labextension/package.json
jupyter_dash/labextension/dist/jupyterlab-dash-v0.4.0.tgz
jupyter_dash/nbextension/jupyter_dash.json
jupyter_dash/nbextension/main.js
jupyter_dash_mp-0.5.0.data/data/etc/jupyter/nbconfig/notebook.d/jupyter_dash.json
jupyter_dash_mp-0.5.0.data/data/share/jupyter/lab/extensions/jupyterlab-dash-v0.4.0.tgz
jupyter_dash_mp-0.5.0.data/data/share/jupyter/nbextensions/jupyter_dash/main.js
jupyter_dash_mp-0.5.0.dist-info/LICENSE.txt
jupyter_dash_mp-0.5.0.dist-info/METADATA
jupyter_dash_mp-0.5.0.dist-info/WHEEL
jupyter_dash_mp-0.5.0.dist-info/top_level.txt
jupyter_dash_mp-0.5.0.dist-info/RECORD
