Metadata-Version: 2.1
Name: jupyter-dash-mp
Version: 0.5.0
Summary: Fork of Jupyter Dash with multiprocessing support: Dash support for the Jupyter notebook interface
Home-page: https://github.com/RobertJN64/jupyter-dash
Author: Robert Nies
License: MIT
Project-URL: Github, https://github.com/RobertJN64/jupyter-dash
Platform: UNKNOWN
Requires-Python: >=3.5
License-File: LICENSE.txt
Requires-Dist: dash
Requires-Dist: requests
Requires-Dist: flask
Requires-Dist: retrying
Requires-Dist: ipython
Requires-Dist: ipykernel
Requires-Dist: ansi2html
Provides-Extra: dev
Requires-Dist: jupyterlab (>=2.0) ; extra == 'dev'
Requires-Dist: notebook (>=6.0) ; extra == 'dev'
Requires-Dist: jupyter-server-proxy ; extra == 'dev'
